README.txt
setup.py
drf_wrapper/__init__.py
drf_wrapper/views.py
drf_wrapper.egg-info/PKG-INFO
drf_wrapper.egg-info/SOURCES.txt
drf_wrapper.egg-info/dependency_links.txt
drf_wrapper.egg-info/requires.txt
drf_wrapper.egg-info/top_level.txt