Metadata-Version: 1.0
Name: drf-wrapper
Version: 0.1
Summary: UNKNOWN
Home-page: https://github.com/shuoli84/drf-wrapper
Author: lishuo
Author-email: shuoli84@gmail.com
License: MIT
Platform: UNKNOWN
